[
    {
        "value": "vacuum",
        "level": 1,
        "hyperlink": "",
        "vocabUri": "",
        "uri": "",
        "synonyms": [],
        "subTerms": []
    },
    {
        "value": "solid phase",
        "level": 1,
        "hyperlink": "",
        "vocabUri": "",
        "uri": "",
        "synonyms": [],
        "subTerms": [
            {
                "value": "ice",
                "level": 2,
                "hyperlink": "",
                "vocabUri": "",
                "uri": "",
                "synonyms": [],
                "subTerms": []
            }
        ]
    },
    {
        "value": "liquid phase",
        "level": 1,
        "hyperlink": "",
        "vocabUri": "",
        "uri": "",
        "synonyms": [],
        "subTerms": [
            {
                "value": "water",
                "level": 2,
                "hyperlink": "",
                "vocabUri": "",
                "uri": "",
                "synonyms": [],
                "subTerms": [
                    {
                        "value": "tap water",
                        "level": 3,
                        "hyperlink": "",
                        "vocabUri": "",
                        "uri": "",
                        "synonyms": [],
                        "subTerms": []
                    },
                    {
                        "value": "demineralized water",
                        "level": 3,
                        "hyperlink": "",
                        "vocabUri": "",
                        "uri": "",
                        "synonyms": [
                            "demi water",
                            "demiwater"
                        ],
                        "subTerms": []
                    },
                    {
                        "value": "de-ionized water",
                        "level": 3,
                        "hyperlink": "",
                        "vocabUri": "",
                        "uri": "",
                        "synonyms": [
                            "deionized water",
                            "DI water",
                            "DIwater",
                            "DI-water"
                        ],
                        "subTerms": []
                    }
                ]
            },
            {
                "value": "salt brine",
                "level": 2,
                "hyperlink": "",
                "vocabUri": "",
                "uri": "",
                "synonyms": [
                    "brine"
                ],
                "subTerms": []
            },
            {
                "value": "oil",
                "level": 2,
                "hyperlink": "",
                "vocabUri": "",
                "uri": "",
                "synonyms": [],
                "subTerms": [
                    {
                        "value": "hydrocarbon oil",
                        "level": 3,
                        "hyperlink": "",
                        "vocabUri": "",
                        "uri": "",
                        "synonyms": [],
                        "subTerms": []
                    },
                    {
                        "value": "silicon oil",
                        "level": 3,
                        "hyperlink": "",
                        "vocabUri": "",
                        "uri": "",
                        "synonyms": [],
                        "subTerms": []
                    },
                    {
                        "value": "mineral oil",
                        "level": 3,
                        "hyperlink": "",
                        "vocabUri": "",
                        "uri": "",
                        "synonyms": [],
                        "subTerms": []
                    }
                ]
            },
            {
                "value": "decane",
                "level": 2,
                "hyperlink": "",
                "vocabUri": "",
                "uri": "",
                "synonyms": [],
                "subTerms": []
            }
        ]
    },
    {
        "value": "gas phase",
        "level": 1,
        "hyperlink": "",
        "vocabUri": "",
        "uri": "",
        "synonyms": [],
        "subTerms": [
            {
                "value": "ambient air",
                "level": 2,
                "hyperlink": "",
                "vocabUri": "",
                "uri": "",
                "synonyms": [
                    "room dry",
                    "roomdry"
                ],
                "subTerms": []
            },
            {
                "value": "hydrogen H2",
                "level": 2,
                "hyperlink": "",
                "vocabUri": "",
                "uri": "",
                "synonyms": [
                    "hydrogen"
                ],
                "subTerms": []
            },
            {
                "value": "oxygen O2",
                "level": 2,
                "hyperlink": "",
                "vocabUri": "",
                "uri": "",
                "synonyms": [
                    "oxygen"
                ],
                "subTerms": []
            },
            {
                "value": "methane CH4",
                "level": 2,
                "hyperlink": "",
                "vocabUri": "",
                "uri": "",
                "synonyms": [
                    "methane"
                ],
                "subTerms": []
            },
            {
                "value": "carbon dioxide CO2",
                "level": 2,
                "hyperlink": "",
                "vocabUri": "",
                "uri": "",
                "synonyms": [
                    "carbondioxide",
                    "carbondyoxide"
                ],
                "subTerms": []
            },
            {
                "value": "nitrogen N2",
                "level": 2,
                "hyperlink": "",
                "vocabUri": "",
                "uri": "",
                "synonyms": [
                    "nitrogen"
                ],
                "subTerms": []
            },
            {
                "value": "argon Ar",
                "level": 2,
                "hyperlink": "",
                "vocabUri": "",
                "uri": "",
                "synonyms": [
                    "argon"
                ],
                "subTerms": []
            }
        ]
    }
]